{"cameraMode":{"drawMode":0,"name":"Shaded","section":"Shading Mode"},"sceneLighting":true,"audioPlay":false,"sceneViewState":{"m_AlwaysRefresh":false,"showFog":true,"showSkybox":true,"showFlares":true,"showImageEffects":true,"showParticleSystems":true,"showVisualEffectGraphs":true,"m_FxEnabled":false},"in2DMode":false,"pivot":{"x":-172.2689208984375,"y":-7.848333358764648,"z":32.87206268310547},"rotation":{"x":-0.2484455406665802,"y":0.33723363280296328,"z":-0.09493045508861542,"w":-0.9034293293952942},"size":16.661130905151368,"orthographic":false}